Metadata-Version: 2.4
Name: yeonjae-universal-llm-service
Version: 1.0.5
Summary: Universal LLM service supporting OpenAI, Anthropic, and local models for code analysis and summarization
Author-email: "CodePing.AI Team" <contact@codeping.ai>
License: MIT
Project-URL: Homepage, https://github.com/yeonjae-work/universal-modules
Project-URL: Repository, https://github.com/yeonjae-work/universal-modules
Project-URL: Issues, https://github.com/yeonjae-work/universal-modules/issues
Project-URL: Changelog, https://github.com/yeonjae-work/universal-modules/blob/main/packages/yeonjae-universal-llm-service/CHANGELOG.md
Keywords: llm,openai,anthropic,ai,machine-learning,nlp,text-generation,code-analysis
Classifier: Development Status :: 5 - Production/Stable
Classifier: Intended Audience :: Developers
Classifier: License :: OSI Approved :: MIT License
Classifier: Operating System :: OS Independent
Classifier: Programming Language :: Python :: 3
Classifier: Programming Language :: Python :: 3.8
Classifier: Programming Language :: Python :: 3.9
Classifier: Programming Language :: Python :: 3.10
Classifier: Programming Language :: Python :: 3.11
Classifier: Programming Language :: Python :: 3.12
Classifier: Topic :: Software Development :: Libraries :: Python Modules
Classifier: Topic :: Scientific/Engineering :: Artificial Intelligence
Classifier: Topic :: Text Processing :: Linguistic
Requires-Python: >=3.8
Requires-Dist: typing-extensions>=4.0.0; python_version < "3.10"
Provides-Extra: openai
Requires-Dist: openai>=1.0.0; extra == "openai"
Provides-Extra: anthropic
Requires-Dist: anthropic>=0.7.0; extra == "anthropic"
Provides-Extra: all
Requires-Dist: openai>=1.0.0; extra == "all"
Requires-Dist: anthropic>=0.7.0; extra == "all"
Provides-Extra: dev
Requires-Dist: pytest>=7.0.0; extra == "dev"
Requires-Dist: pytest-asyncio>=0.21.0; extra == "dev"
Requires-Dist: pytest-mock>=3.10.0; extra == "dev"
Requires-Dist: black>=23.0.0; extra == "dev"
Requires-Dist: isort>=5.12.0; extra == "dev"
Requires-Dist: flake8>=6.0.0; extra == "dev"
Requires-Dist: mypy>=1.0.0; extra == "dev"
Requires-Dist: responses>=0.23.0; extra == "dev"
